itkwasm_transform_io/__init__.py
itkwasm_transform_io/_version.py
itkwasm_transform_io/hdf5_read_transform.py
itkwasm_transform_io/hdf5_read_transform_async.py
itkwasm_transform_io/hdf5_write_transform.py
itkwasm_transform_io/hdf5_write_transform_async.py
itkwasm_transform_io/mat_read_transform.py
itkwasm_transform_io/mat_read_transform_async.py
itkwasm_transform_io/mat_write_transform.py
itkwasm_transform_io/mat_write_transform_async.py
itkwasm_transform_io/mnc_read_transform.py
itkwasm_transform_io/mnc_read_transform_async.py
itkwasm_transform_io/mnc_write_transform.py
itkwasm_transform_io/mnc_write_transform_async.py
itkwasm_transform_io/read_transform.py
itkwasm_transform_io/read_transform_async.py
itkwasm_transform_io/txt_read_transform.py
itkwasm_transform_io/txt_read_transform_async.py
itkwasm_transform_io/txt_write_transform.py
itkwasm_transform_io/txt_write_transform_async.py
itkwasm_transform_io/wasm_read_transform.py
itkwasm_transform_io/wasm_read_transform_async.py
itkwasm_transform_io/wasm_write_transform.py
itkwasm_transform_io/wasm_write_transform_async.py
itkwasm_transform_io/wasm_zstd_read_transform.py
itkwasm_transform_io/wasm_zstd_read_transform_async.py
itkwasm_transform_io/wasm_zstd_write_transform.py
itkwasm_transform_io/wasm_zstd_write_transform_async.py
itkwasm_transform_io/write_transform.py
itkwasm_transform_io/write_transform_async.py
itkwasm_transform_io-1.1.0.dist-info/METADATA
itkwasm_transform_io-1.1.0.dist-info/WHEEL
itkwasm_transform_io-1.1.0.dist-info/RECORD
